stockcli/__init__.py
stockcli/main.py
stockcli-0.2.0.dist-info/entry_points.txt
stockcli-0.2.0.dist-info/WHEEL
stockcli-0.2.0.dist-info/METADATA
stockcli-0.2.0.dist-info/RECORD
